sabana/__init__.py
sabana/cc.py
sabana/common.py
sabana/instance.py
sabana/program.py
sabana/requests.py
sabana/responses.py
sabana/sabana_pb2.py
sabana-0.1.24.dist-info/WHEEL
sabana-0.1.24.dist-info/METADATA
sabana-0.1.24.dist-info/RECORD
