Metadata-Version: 2.1
Name: sabana
Version: 0.1.24
Summary: Classes to interact with Sabana. Meet us at https://sabana.io
Home-page: https://sabana.io/
License: Apache-2.0
Author: Sabana Technologies, Inc
Requires-Python: >=3.8,<4.0
Classifier: License :: OSI Approved :: Apache Software License
Classifier: Programming Language :: Python :: 3
Classifier: Programming Language :: Python :: 3.10
Classifier: Programming Language :: Python :: 3.8
Classifier: Programming Language :: Python :: 3.9
Requires-Dist: numpy (>=1.21.6,<2.0.0)
Requires-Dist: pathlib (>=1.0.1,<2.0.0)
Requires-Dist: protobuf (>=4.21.1,<5.0.0)
Requires-Dist: python-jose (>=3.3.0,<4.0.0)
Requires-Dist: requests (>=2.28.0,<3.0.0)
Requires-Dist: validators (>=0.20.0,<0.21.0)
